{"cameraMode":{"drawMode":0,"name":"Shaded","section":"Shading Mode"},"sceneLighting":true,"audioPlay":false,"sceneViewState":{"showFog":true,"showMaterialUpdate":false,"showSkybox":true,"showFlares":true,"showImageEffects":true,"showParticleSystems":true},"in2DMode":false,"pivot":{"x":14.962003707885743,"y":-0.9910383224487305,"z":-1.1068782806396485},"rotation":{"x":-0.10611812025308609,"y":-0.8072221279144287,"z":0.15293121337890626,"w":-0.5601280331611633},"size":23.8414249420166,"orthographic":false}